fifo.xpr/fifo/fifo.srcs/sources_1/new/synchroniser.v
module Synchronizer (
    input wire wr_clk,
    input wire rd_clk,
    input wire [N-1:0] b_wr_ptr,
    input wire [N-1:0] b_rd_ptr,
    output reg [N-1:0] sync_wr_ptr,
    output reg [N-1:0] sync_rd_ptr
);
    parameter N = 4;

    always @(posedge rd_clk) begin
        sync_wr_ptr <= b_wr_ptr;
    end

    always @(posedge wr_clk) begin
        sync_rd_ptr <= b_rd_ptr;
    end
endmodule

fifo.xpr/fifo/fifo.srcs/sources_1/new/flag_logic.v
module FlagLogic (
    input wire [N-1:0] b_wr_ptr,
    input wire [N-1:0] b_rd_ptr,
    input wire MSB_wr_ptr,
    input wire MSB_rd_ptr,
    output wire f_full,
    output wire f_empty
);
    parameter N = 4;

    assign f_full = (b_wr_ptr == b_rd_ptr) && (MSB_wr_ptr != MSB_rd_ptr);
    assign f_empty = (b_wr_ptr == b_rd_ptr) && (MSB_wr_ptr == MSB_rd_ptr);
endmodule

fifo.xpr/fifo/fifo.srcs/sources_1/new/dual_port_ram.v
`timescale 1ns / 1ps
module DualPortSRAM (
    input wire wr_clk,
    input wire rd_clk,
    input wire [N-1:0] b_wr_ptr,
    input wire [N-1:0] b_rd_ptr,
    input wire [D-1:0] wr_data_in,
    output wire [D-1:0] rd_data_out,
    input wire wr_en_in,
    input wire rd_en_in
);
    parameter N = 4;
    parameter D = 8;
    
    reg [D-1:0] memory [(2**N)-1:0];
    reg [D-1:0] data_out;

    always @(posedge wr_clk) begin
        if (wr_en_in) begin
            memory[b_wr_ptr] <= wr_data_in;
        end
    end

    always @(posedge rd_clk) begin
        if (rd_en_in) begin
            data_out <= memory[b_rd_ptr];
        end
    end

    assign rd_data_out = data_out;
endmodule

fifo.xpr/fifo/fifo.srcs/sources_1/new/read_control.v
`timescale 1ns / 1ps
module read_control (
    input wire rd_clk,
    input wire reset_n,
    input wire f_empty,
    output reg [N-1:0] b_rd_ptr,
    output wire MSB_rd_ptr
);
    parameter N = 4;

    always @(posedge rd_clk or negedge reset_n) begin
        if (!reset_n) begin
            b_rd_ptr <= 0;
        end else if (!f_empty) begin
            b_rd_ptr <= b_rd_ptr + 1;
        end
    end

    assign MSB_rd_ptr = b_rd_ptr[N-1];
endmodule

fifo.xpr/fifo/fifo.srcs/sources_1/new/write_control.v
`timescale 1ns / 1ps
module write_control (
    input wire wr_clk,
    input wire reset_n,
    input wire f_full,
    output reg [N-1:0] b_wr_ptr,
    output wire MSB_wr_ptr
);
    parameter N = 4;

    always @(posedge wr_clk or negedge reset_n) begin
        if (!reset_n) begin
            b_wr_ptr <= 0;
        end else if (!f_full) begin
            b_wr_ptr <= b_wr_ptr + 1;
        end
    end

    assign MSB_wr_ptr = b_wr_ptr[N-1];
endmodule

fifo.xpr/fifo/fifo.srcs/sources_1/new/fifo.v
`timescale 1ns / 1ps
module FIFO (
    input wire wr_clk,
    input wire rd_clk,
    input wire reset_n,
    input wire [D-1:0] wr_data_in,
    output wire [D-1:0] rd_data_out,
    input wire wr_en_in,
    input wire rd_en_in,
    output wire f_full,
    output wire f_empty
);
    parameter N = 4;
    parameter D = 8;

    wire [N-1:0] b_wr_ptr, b_rd_ptr;
    wire MSB_wr_ptr, MSB_rd_ptr;

    write_control #(N) write_ctrl (
        .wr_clk(wr_clk),
        .reset_n(reset_n),
        .f_full(f_full),
        .b_wr_ptr(b_wr_ptr),
        .MSB_wr_ptr(MSB_wr_ptr)
    );

    read_control #(N) read_ctrl (
        .rd_clk(rd_clk),
        .reset_n(reset_n),
        .f_empty(f_empty),
        .b_rd_ptr(b_rd_ptr),
        .MSB_rd_ptr(MSB_rd_ptr)
    );

    DualPortSRAM #(N, D) sram (
        .wr_clk(wr_clk),
        .rd_clk(rd_clk),
        .b_wr_ptr(b_wr_ptr),
        .b_rd_ptr(b_rd_ptr),
        .wr_data_in(wr_data_in),
        .rd_data_out(rd_data_out),
        .wr_en_in(wr_en_in),
        .rd_en_in(rd_en_in)
    );

    FlagLogic #(N) flag_logic (
        .b_wr_ptr(b_wr_ptr),
        .b_rd_ptr(b_rd_ptr),
        .MSB_wr_ptr(MSB_wr_ptr),
        .MSB_rd_ptr(MSB_rd_ptr),
        .f_full(f_full),
        .f_empty(f_empty)
    );

    Synchronizer #(N) synchronizer (
        .wr_clk(wr_clk),
        .rd_clk(rd_clk),
        .b_wr_ptr(b_wr_ptr),
        .b_rd_ptr(b_rd_ptr),
        .sync_wr_ptr(),
        .sync_rd_ptr()
    );
endmodule

fifo.xpr/fifo/fifo.srcs/sim_1/new/fifo_tb.v
module FIFO_tb;
    reg wr_clk;
    reg rd_clk;
    reg reset_n;
    reg [7:0] wr_data_in;
    wire [7:0] rd_data_out;
    reg wr_en_in;
    reg rd_en_in;
    wire f_full;
    wire f_empty;

    FIFO #(4, 8) fifo (
        .wr_clk(wr_clk),
        .rd_clk(rd_clk),
        .reset_n(reset_n),
        .wr_data_in(wr_data_in),
        .rd_data_out(rd_data_out),
        .wr_en_in(wr_en_in),
        .rd_en_in(rd_en_in),
        .f_full(f_full),
        .f_empty(f_empty)
    );

    initial begin
        // Initialize clocks
        wr_clk = 0;
        rd_clk = 0;
        reset_n = 0;
        wr_en_in = 0;
        rd_en_in = 0;
        wr_data_in = 8'h00;
        
        // Reset the FIFO
        #10 reset_n = 1;
        
        // Write to FIFO
        #10 wr_en_in = 1; wr_data_in = 8'hAA;
        #20 wr_en_in = 1; wr_data_in = 8'hBB;
        #20 wr_en_in = 1; wr_data_in = 8'hCC;
        #20 wr_en_in = 0;
        
        // Read from FIFO
        #20 rd_en_in = 1;
        #40 rd_en_in = 0;
        
        // Finish simulation
        #100 $finish;
    end

    always #5 wr_clk = ~wr_clk;
    always #10 rd_clk = ~rd_clk;

    initial begin
        $dumpfile("fifo_tb.vcd");
        $dumpvars(0, FIFO_tb);
    end
endmodule

fifo.xpr/fifo/fifo.sim/sim_1/behav/xsim/fifo_tb.vcd
$date
   Sun Jul 14 21:10:45 2024
$end
$version
  2018.3
$end
$timescale
  1ps
$end
$scope module FIFO_tb $end
$var reg 1 ! wr_clk $end
$var reg 1 " rd_clk $end
$var reg 1 # reset_n $end
$var reg 8 $ wr_data_in [7:0] $end
$var wire 8 % rd_data_out [7:0] $end
$var reg 1 & wr_en_in $end
$var reg 1 ' rd_en_in $end
$var wire 1 ( f_full $end
$var wire 1 ) f_empty $end
$scope module fifo $end
$var wire 1 * wr_clk $end
$var wire 1 + rd_clk $end
$var wire 1 , reset_n $end
$var wire 8 - wr_data_in [7:0] $end
$var wire 8 % rd_data_out [7:0] $end
$var wire 1 . wr_en_in $end
$var wire 1 / rd_en_in $end
$var wire 1 ( f_full $end
$var wire 1 ) f_empty $end
$var wire 4 0 b_wr_ptr [3:0] $end
$var wire 4 1 b_rd_ptr [3:0] $end
$var wire 1 2 MSB_wr_ptr $end
$var wire 1 3 MSB_rd_ptr $end
$var parameter 32 4 N [31:0] $end
$var parameter 32 5 D [31:0] $end
$scope module write_ctrl $end
$var wire 1 * wr_clk $end
$var wire 1 , reset_n $end
$var wire 1 ( f_full $end
$var reg 4 6 b_wr_ptr [3:0] $end
$var wire 1 2 MSB_wr_ptr $end
$var parameter 32 7 N [31:0] $end
$upscope $end
$scope module read_ctrl $end
$var wire 1 + rd_clk $end
$var wire 1 , reset_n $end
$var wire 1 ) f_empty $end
$var reg 4 8 b_rd_ptr [3:0] $end
$var wire 1 3 MSB_rd_ptr $end
$var parameter 32 9 N [31:0] $end
$upscope $end
$scope module sram $end
$var wire 1 * wr_clk $end
$var wire 1 + rd_clk $end
$var wire 4 0 b_wr_ptr [3:0] $end
$var wire 4 1 b_rd_ptr [3:0] $end
$var wire 8 - wr_data_in [7:0] $end
$var wire 8 % rd_data_out [7:0] $end
$var wire 1 . wr_en_in $end
$var wire 1 / rd_en_in $end
$var reg 8 : data_out [7:0] $end
$var parameter 32 ; N [31:0] $end
$var parameter 32 < D [31:0] $end
$upscope $end
$scope module flag_logic $end
$var wire 4 0 b_wr_ptr [3:0] $end
$var wire 4 1 b_rd_ptr [3:0] $end
$var wire 1 2 MSB_wr_ptr $end
$var wire 1 3 MSB_rd_ptr $end
$var wire 1 ( f_full $end
$var wire 1 ) f_empty $end
$var parameter 32 = N [31:0] $end
$upscope $end
$scope module synchronizer $end
$var wire 1 * wr_clk $end
$var wire 1 + rd_clk $end
$var wire 4 0 b_wr_ptr [3:0] $end
$var wire 4 1 b_rd_ptr [3:0] $end
$var reg 4 > sync_wr_ptr [3:0] $end
$var reg 4 ? sync_rd_ptr [3:0] $end
$var parameter 32 @ N [31:0] $end
$upscope $end
$upscope $end
$upscope $end
$enddefinitions $end
#0
$dumpvars
0!
0"
0#
b0 $
bx %
0&
0'
0(
1)
0*
0+
0,
b0 -
0.
0/
b0 0
b0 1
02
03
b100 4
b1000 5
b0 6
b100 7
b0 8
b100 9
bx :
b100 ;
b1000 <
b100 =
bx >
bx ?
b100 @
$end
#5000
1!
1*
b0 ?
#10000
0!
1"
1#
0*
1+
1,
b0 >
#15000
1!
0)
1*
b1 0
b1 6
#20000
0!
0"
b10101010 $
1&
0*
0+
b10101010 -
1.
#25000
1!
1*
b10 0
b10 6
#30000
0!
1"
0*
1+
b1 1
b1 8
b10 >
#35000
1!
1*
b11 0
b11 6
b1 ?
#40000
0!
0"
b10111011 $
0*
0+
b10111011 -
#45000
1!
1*
b100 0
b100 6
#50000
0!
1"
0*
1+
b10 1
b10 8
b100 >
#55000
1!
1*
b101 0
b101 6
b10 ?
#60000
0!
0"
b11001100 $
0*
0+
b11001100 -
#65000
1!
1*
b110 0
b110 6
#70000
0!
1"
0*
1+
b11 1
b11 8
b110 >
#75000
1!
1*
b111 0
b111 6
b11 ?
#80000
0!
0"
0&
0*
0+
0.
#85000
1!
1*
b1000 0
12
b1000 6
#90000
0!
1"
0*
1+
b100 1
b100 8
b1000 >
#95000
1!
1*
b1001 0
b1001 6
b100 ?
#100000
0!
0"
1'
0*
0+
1/
#105000
1!
1*
b1010 0
b1010 6
#110000
0!
1"
b10111011 %
0*
1+
b101 1
b101 8
b10111011 :
b1010 >
#115000
1!
1*
b1011 0
b1011 6
b101 ?
#120000
0!
0"
0*
0+
#125000
1!
1*
b1100 0
b1100 6
#130000
0!
1"
b11001100 %
0*
1+
b110 1
b110 8
b11001100 :
b1100 >
#135000
1!
1*
b1101 0
b1101 6
b110 ?
#140000
0!
0"
0'
0*
0+
0/
#145000
1!
1*
b1110 0
b1110 6
#150000
0!
1"
0*
1+
b111 1
b111 8
b1110 >
#155000
1!
1*
b1111 0
b1111 6
b111 ?
#160000
0!
0"
0*
0+
#165000
1!
1*
b0 0
02
b0 6
#170000
0!
1"
0*
1+
b1000 1
13
b1000 8
b0 >
#175000
1!
1*
b1 0
b1 6
b1000 ?
#180000
0!
0"
0*
0+
#185000
1!
1*
b10 0
b10 6
#190000
0!
1"
0*
1+
b1001 1
b1001 8
b10 >
#195000
1!
1*
b11 0
b11 6
b1001 ?
#200000
0!
0"
0*
0+
#205000
1!
1*
b100 0
b100 6
#210000
0!
1"
0*
1+
b1010 1
b1010 8
b100 >
#215000
1!
1*
b101 0
b101 6
b1010 ?
#220000
0!
0"
0*
0+
#225000
1!
1*
b110 0
b110 6
#230000
0!
1"
0*
1+
b1011 1
b1011 8
b110 >
